anonymate/__init__.py
anonymate/anonymizer.py
anonymate/encryption.py
anonymate/faker_util.py
anonymate/utils.py
AnonyMate-0.1.6.dist-info/LICENSE
AnonyMate-0.1.6.dist-info/METADATA
AnonyMate-0.1.6.dist-info/WHEEL
AnonyMate-0.1.6.dist-info/top_level.txt
AnonyMate-0.1.6.dist-info/RECORD
