Metadata-Version: 2.1
Name: AnonyMate
Version: 0.1.6
Summary: A comprehensive toolkit for data anonymization, masking, and encryption.
Home-page: https://github.com/PasinduBandaraa/AnonyMate
Author: Pasindu Bandara
Author-email: pasindubandara99@gmail.com
Classifier: Programming Language :: Python :: 3
Classifier: License :: OSI Approved :: MIT License
Classifier: Operating System :: OS Independent
Requires-Python: >=3.6
License-File: LICENSE
Requires-Dist: cryptography
Requires-Dist: faker
